hangman_terminal/__init__.py
hangman_terminal/animation.py
hangman_terminal/main.py
hangman_terminal-1.0.1.dist-info/licenses/License.txt
hangman_terminal-1.0.1.dist-info/METADATA
hangman_terminal-1.0.1.dist-info/WHEEL
hangman_terminal-1.0.1.dist-info/entry_points.txt
hangman_terminal-1.0.1.dist-info/top_level.txt
hangman_terminal-1.0.1.dist-info/RECORD
