Metadata-Version: 2.4
Name: hangman-terminal
Version: 1.0.1
Summary: Hangman in terminal
Home-page: https://github.com/menonkrishna57/Hangman-Game-in-Python
Author: Krishna Menon
Author-email: menonkrishna57@gmail.com
License: MIT
Classifier: Programming Language :: Python :: 3
Classifier: License :: OSI Approved :: MIT License
Classifier: Operating System :: OS Independent
License-File: License.txt
Dynamic: author
Dynamic: author-email
Dynamic: classifier
Dynamic: description
Dynamic: description-content-type
Dynamic: home-page
Dynamic: license
Dynamic: license-file
Dynamic: summary
